mayidaili/__init__.py
mayidaili/scrapy_middleware.py
mayidaili-1.0.2.dist-info/METADATA
mayidaili-1.0.2.dist-info/WHEEL
mayidaili-1.0.2.dist-info/top_level.txt
mayidaili-1.0.2.dist-info/RECORD
