Metadata-Version: 2.1
Name: mayidaili
Version: 1.0.2
Summary: Mayidaili requests
Home-page: UNKNOWN
Author: UNKNOWN
Author-email: UNKNOWN
License: UNKNOWN
Platform: UNKNOWN
Requires-Dist: requests
